qris_saweria/__init__.py
qris_saweria/core.py
qris_saweria/template.png
qris_saweria-1.0.1.dist-info/LICENSE
qris_saweria-1.0.1.dist-info/METADATA
qris_saweria-1.0.1.dist-info/WHEEL
qris_saweria-1.0.1.dist-info/top_level.txt
qris_saweria-1.0.1.dist-info/RECORD
