Metadata-Version: 2.1
Name: qris-saweria
Version: 1.0.1
Summary: API tidak resmi saweria.co untuk membuat dan cek QRIS otomatis
Home-page: https://github.com/AutoFTbot/saweria-qris
Author: AutoFTbot
Author-email: aginazharmhlutpi14@gmail.com
License: MIT
Project-URL: Source, https://github.com/AutoFTbot/saweria-qris
Project-URL: Donate, https://ko-fi.com/FighterTunnel
Classifier: Programming Language :: Python :: 3
Classifier: License :: OSI Approved :: MIT License
Classifier: Operating System :: OS Independent
Requires-Python: >=3.7
License-File: LICENSE
Requires-Dist: requests
Requires-Dist: bs4
Requires-Dist: qrcode
Requires-Dist: Pillow
